cdk_tree_parser/__init__.py
cdk_tree_parser/py.typed
cdk_tree_parser/_jsii/__init__.py
cdk_tree_parser/_jsii/cdk-utilities@0.0.7.jsii.tgz
cdk_tree_parser-0.0.7.dist-info/LICENSE
cdk_tree_parser-0.0.7.dist-info/METADATA
cdk_tree_parser-0.0.7.dist-info/WHEEL
cdk_tree_parser-0.0.7.dist-info/top_level.txt
cdk_tree_parser-0.0.7.dist-info/RECORD
