Metadata-Version: 2.1
Name: cdk-tree-parser
Version: 0.0.7
Summary: cdk-utilities
Home-page: https://git-codecommit.us-east-1.amazonaws.com/v1/repos/cdk-utilities
Author: Hasan Abu-Rayyan<hasanaburayyan21@gmail.com>
License: Apache-2.0
Project-URL: Source, https://git-codecommit.us-east-1.amazonaws.com/v1/repos/cdk-utilities
Platform: UNKNOWN
Classifier: Intended Audience :: Developers
Classifier: Operating System :: OS Independent
Classifier: Programming Language :: JavaScript
Classifier: Programming Language :: Python :: 3 :: Only
Classifier: Programming Language :: Python :: 3.6
Classifier: Programming Language :: Python :: 3.7
Classifier: Programming Language :: Python :: 3.8
Classifier: Programming Language :: Python :: 3.9
Classifier: Typing :: Typed
Classifier: Development Status :: 5 - Production/Stable
Classifier: License :: OSI Approved
Requires-Python: >=3.6
Requires-Dist: aws-cdk.aws-s3 (<2.0.0,>=1.117.0)
Requires-Dist: aws-cdk.cloud-assembly-schema (<2.0.0,>=1.117.0)
Requires-Dist: aws-cdk.core (<2.0.0,>=1.117.0)
Requires-Dist: constructs (<4.0.0,>=3.2.27)
Requires-Dist: jsii (<2.0.0,>=1.32.0)
Requires-Dist: publication (>=0.0.3)
